Metadata-Version: 2.1
Name: cmdstan-builder
Version: 0.0.3
Summary: A package to build the cmdstan binary and use it as an extension to EvalML
Home-page: https://github.com/alteryx/cmdstan_ext/
Author: Alteryx, Inc.
Author-email: support@featurelabs.com
License: BSD-3-Clause
Platform: UNKNOWN
Requires-Python: >=3.7
